zenodo_sync/__init__.py
zenodo_sync/cli.py
zenodo_sync/core.py
zenodo_sync/exceptions.py
zenodo_sync-0.1.0.dist-info/licenses/LICENSE
zenodo_sync-0.1.0.dist-info/METADATA
zenodo_sync-0.1.0.dist-info/WHEEL
zenodo_sync-0.1.0.dist-info/entry_points.txt
zenodo_sync-0.1.0.dist-info/top_level.txt
zenodo_sync-0.1.0.dist-info/RECORD
