Metadata-Version: 2.4
Name: zenodo-sync
Version: 0.1.0
Summary: A lightweight CLI and Python library to synchronise local research data, results and analysis artifacts with Zenodo
Author-email: CausalIQ <info@causaliq.com>
Maintainer-email: CausalIQ <info@causaliq.com>
License: MIT
Project-URL: Homepage, https://github.com/causaliq/zenodo-sync
Project-URL: Documentation, https://github.com/causaliq/zenodo-sync#readme
Project-URL: Repository, https://github.com/causaliq/zenodo-sync
Project-URL: Bug Tracker, https://github.com/causaliq/zenodo-sync/issues
Keywords: zenodo,research,data,reproducible,science,publishing
Classifier: Development Status :: 2 - Pre-Alpha
Classifier: Intended Audience :: Science/Research
Classifier: License :: OSI Approved :: MIT License
Classifier: Operating System :: OS Independent
Classifier: Programming Language :: Python :: 3
Classifier: Programming Language :: Python :: 3.9
Classifier: Programming Language :: Python :: 3.10
Classifier: Programming Language :: Python :: 3.11
Classifier: Programming Language :: Python :: 3.12
Classifier: Topic :: Scientific/Engineering
Classifier: Topic :: Software Development :: Libraries :: Python Modules
Requires-Python: >=3.9
License-File: LICENSE
Requires-Dist: requests>=2.28.0
Requires-Dist: click>=8.0.0
Requires-Dist: pydantic>=2.0.0
Requires-Dist: python-dotenv>=0.19.0
Provides-Extra: dev
Requires-Dist: pytest>=7.0.0; extra == "dev"
Requires-Dist: pytest-cov>=4.0.0; extra == "dev"
Requires-Dist: pytest-mock>=3.10.0; extra == "dev"
Requires-Dist: black>=22.0.0; extra == "dev"
Requires-Dist: isort>=5.10.0; extra == "dev"
Requires-Dist: flake8>=5.0.0; extra == "dev"
Requires-Dist: mypy>=1.0.0; extra == "dev"
Requires-Dist: pre-commit>=2.20.0; extra == "dev"
Requires-Dist: build>=0.8.0; extra == "dev"
Requires-Dist: twine>=4.0.0; extra == "dev"
Provides-Extra: test
Requires-Dist: pytest>=7.0.0; extra == "test"
Requires-Dist: pytest-cov>=4.0.0; extra == "test"
Requires-Dist: pytest-mock>=3.10.0; extra == "test"
Provides-Extra: docs
Requires-Dist: sphinx>=5.0.0; extra == "docs"
Requires-Dist: sphinx-rtd-theme>=1.0.0; extra == "docs"
Dynamic: license-file
